{
  "generated_at": "Apr 22, 2026 at 7:35 PM",
  "generated_ts": "2026-04-22T23:35:01.659534+00:00",
  "commits": [
    {
      "sha": "d71e5134",
      "subject": "fix(auto-patch): apply_agent_finding.py:_get_recent_agent_findings \u2014 Ensure DB connection is always closed using try/finally",
      "when": "4 minutes ago",
      "tag": "autonomous"
    },
    {
      "sha": "014948be",
      "subject": "feat(code-read): add 3rd rotation target \u2014 apply_agent_finding.py",
      "when": "12 minutes ago",
      "tag": "autonomous"
    },
    {
      "sha": "10b0d726",
      "subject": "fix(queue): queue_doctor pruned+refreshed 0 removed, 4 agent tasks added \u2014 Apr 22, 2026 at 7:21 PM",
      "when": "13 minutes ago",
      "tag": "autonomous"
    },
    {
      "sha": "7c3e008f",
      "subject": "fix(queue): queue_doctor pruned+refreshed 0 removed, 4 agent tasks added \u2014 Apr 22, 2026 at 7:20 PM",
      "when": "15 minutes ago",
      "tag": "autonomous"
    },
    {
      "sha": "eed6b42c",
      "subject": "fix(queue): queue_doctor pruned+refreshed 0 removed, 4 agent tasks added \u2014 Apr 22, 2026 at 7:15 PM",
      "when": "19 minutes ago",
      "tag": "autonomous"
    },
    {
      "sha": "f37ed98a",
      "subject": "feat(auto-rotate): queue_doctor.py auto-rotates code-read targets based on recent auto-patches",
      "when": "20 minutes ago",
      "tag": "autonomous"
    },
    {
      "sha": "a4a9326a",
      "subject": "fix(queue): queue_doctor pruned+refreshed 0 removed, 4 agent tasks added \u2014 Apr 22, 2026 at 7:10 PM",
      "when": "25 minutes ago",
      "tag": "autonomous"
    },
    {
      "sha": "80f7ba95",
      "subject": "fix(queue): queue_doctor pruned+refreshed 0 removed, 4 agent tasks added \u2014 Apr 22, 2026 at 7:09 PM",
      "when": "26 minutes ago",
      "tag": "autonomous"
    },
    {
      "sha": "cf7129cf",
      "subject": "docs(session-GG): update PLAN+NEXT_SESSION+IDEAS with session state",
      "when": "38 minutes ago",
      "tag": "manual-session"
    },
    {
      "sha": "33cac16c",
      "subject": "fix(queue): queue_doctor pruned+refreshed 0 removed, 4 agent tasks added \u2014 Apr 22, 2026 at 6:55 PM",
      "when": "40 minutes ago",
      "tag": "autonomous"
    },
    {
      "sha": "b75d8ec5",
      "subject": "fix(patch-loop): extend debounce to 4h, rotate code-read target to detect_cascading_failures",
      "when": "40 minutes ago",
      "tag": "autonomous"
    },
    {
      "sha": "b49d6fa0",
      "subject": "fix(queue): queue_doctor pruned+refreshed 0 removed, 4 agent tasks added \u2014 Apr 22, 2026 at 6:50 PM",
      "when": "45 minutes ago",
      "tag": "autonomous"
    },
    {
      "sha": "ba1631be",
      "subject": "fix(queue): queue_doctor pruned+refreshed 0 removed, 4 agent tasks added \u2014 Apr 22, 2026 at 6:45 PM",
      "when": "50 minutes ago",
      "tag": "autonomous"
    },
    {
      "sha": "36ee07c8",
      "subject": "fix(auto-patch): investigate.py:auto_generate_tasks_from_findings \u2014 Add guard for malformed finding tuples to prevent IndexError",
      "when": "54 minutes ago",
      "tag": "autonomous"
    },
    {
      "sha": "737501bd",
      "subject": "fix(queue): queue_doctor pruned+refreshed 0 removed, 4 agent tasks added \u2014 Apr 22, 2026 at 6:30 PM",
      "when": "64 minutes ago",
      "tag": "autonomous"
    }
  ],
  "commits_today": {
    "total": 112,
    "autonomous": 80,
    "manual": 32
  },
  "recent_tasks": [
    {
      "label": "\ud83d\udd27 patch_dispatcher.py",
      "handler": "script",
      "q": 0.7,
      "q_class": "high",
      "when": "2026-04-22 23:35",
      "finding": null
    },
    {
      "label": "\ud83d\udd27 apply_agent_finding.py",
      "handler": "script",
      "q": 0.7,
      "q_class": "high",
      "when": "2026-04-22 23:30",
      "finding": null
    },
    {
      "label": "\ud83e\udde0 The task 'Generate script-based code improvement repo",
      "handler": "openclaw",
      "q": 0.2,
      "q_class": "low",
      "when": "2026-04-22 23:30",
      "finding": null
    },
    {
      "label": "\ud83d\udd27 backup_state.py",
      "handler": "script",
      "q": 0.7,
      "q_class": "high",
      "when": "2026-04-22 23:30",
      "finding": null
    },
    {
      "label": "\ud83d\udd27 self_improver.py",
      "handler": "script",
      "q": 0.7,
      "q_class": "high",
      "when": "2026-04-22 23:30",
      "finding": null
    },
    {
      "label": "\ud83d\udd27 export_status.py [2026-04-22T23:00]",
      "handler": "script",
      "q": 0.7,
      "q_class": "high",
      "when": "2026-04-22 23:30",
      "finding": null
    },
    {
      "label": "\ud83e\udde0 Read hub/logs/orchestrator.log last 30 lines. Identif",
      "handler": "openclaw",
      "q": 0.7,
      "q_class": "high",
      "when": "2026-04-22 23:30",
      "finding": null
    },
    {
      "label": "\ud83d\udd27 orchestrator_quality.py",
      "handler": "script",
      "q": 0.7,
      "q_class": "high",
      "when": "2026-04-22 23:30",
      "finding": null
    },
    {
      "label": "\ud83d\udd27 task_quality_audit.py",
      "handler": "script",
      "q": 0.7,
      "q_class": "high",
      "when": "2026-04-22 23:30",
      "finding": null
    },
    {
      "label": "\ud83d\udd27 export_status.py",
      "handler": "script",
      "q": 0.7,
      "q_class": "high",
      "when": "2026-04-22 23:25",
      "finding": null
    },
    {
      "label": "\ud83d\udd27 budget_tracker.py",
      "handler": "script",
      "q": 0.7,
      "q_class": "high",
      "when": "2026-04-22 23:25",
      "finding": null
    },
    {
      "label": "\ud83d\udd27 link_checker.py",
      "handler": "script",
      "q": 0.7,
      "q_class": "high",
      "when": "2026-04-22 23:25",
      "finding": null
    },
    {
      "label": "\ud83e\udd16 reality-checker Specific low-q tasks last 24h: #1925(q",
      "handler": "openclaw",
      "q": 0.65,
      "q_class": "high",
      "when": "2026-04-22 23:25",
      "finding": null
    },
    {
      "label": "\ud83e\udd16 sre code-read-store: Read hub_scripts/apply_agent_find",
      "handler": "openclaw",
      "q": 0.7,
      "q_class": "high",
      "when": "2026-04-22 23:25",
      "finding": "[agent:sre][q=0.300]hub/scripts/apply_agent_finding.py | _get_recent_agent_findings | Ensure DB connection is always closed using try/finally"
    },
    {
      "label": "\ud83d\udd27 audit_trend_tracker.py",
      "handler": "script",
      "q": 0.7,
      "q_class": "high",
      "when": "2026-04-22 23:25",
      "finding": null
    },
    {
      "label": "\ud83e\udd16 sre code-read-store: Read hub_scripts/orchestrator_qua",
      "handler": "openclaw",
      "q": 0.7,
      "q_class": "high",
      "when": "2026-04-22 23:25",
      "finding": "[agent:sre][q=0.300]hub/scripts/orchestrator_quality.py | _categorize_task_tier | Expand web search handler check beyond 'openclaw' to catch other search tools."
    },
    {
      "label": "\ud83e\udd16 sre code-read-store: Read hub_scripts/investigate.py l",
      "handler": "openclaw",
      "q": 0.7,
      "q_class": "high",
      "when": "2026-04-22 23:25",
      "finding": null
    },
    {
      "label": "\ud83d\udd27 gen_dashboard_data.py",
      "handler": "script",
      "q": 0.76,
      "q_class": "high",
      "when": "2026-04-22 23:20",
      "finding": null
    },
    {
      "label": "\ud83d\udd27 queue_doctor.py",
      "handler": "script",
      "q": 0.74,
      "q_class": "high",
      "when": "2026-04-22 23:20",
      "finding": null
    },
    {
      "label": "\ud83d\udd27 sync_scripts_to_workspace.py",
      "handler": "script",
      "q": 0.7,
      "q_class": "high",
      "when": "2026-04-22 23:20",
      "finding": null
    }
  ],
  "handler_stats": [
    {
      "handler": "script",
      "runs": 160,
      "avg_q": 0.71
    },
    {
      "handler": "openclaw",
      "runs": 75,
      "avg_q": 0.61
    }
  ],
  "loop_events": [
    {
      "name": "apply_agent_finding.py",
      "q": 0.7,
      "when": "2026-04-22 23:30",
      "output": "und finding from task #1935 (2026-04-22 23:25:22)"
    },
    {
      "name": "self_improver.py",
      "q": 0.7,
      "when": "2026-04-22 23:30",
      "output": ""
    },
    {
      "name": "apply_agent_finding.py",
      "q": 0.7,
      "when": "2026-04-22 23:25",
      "output": "[agent:sre][q=0.300]hub/scripts/apply_agent_finding.py | _get_recent_agent_findings | Ensure DB conn"
    },
    {
      "name": "self_improver.py",
      "q": 0.7,
      "when": "2026-04-22 23:20",
      "output": ""
    },
    {
      "name": "apply_agent_finding.py",
      "q": 0.7,
      "when": "2026-04-22 23:20",
      "output": "ipping task #1914 \u2014 unparseable output"
    },
    {
      "name": "self_improver.py",
      "q": 0.7,
      "when": "2026-04-22 23:05",
      "output": ""
    },
    {
      "name": "apply_agent_finding.py",
      "q": 0.7,
      "when": "2026-04-22 23:05",
      "output": "ipping task #1891 \u2014 unparseable output"
    },
    {
      "name": "self_improver.py",
      "q": 0.7,
      "when": "2026-04-22 22:55",
      "output": ""
    }
  ],
  "latest_finding": {
    "pattern": "[agent:sre][q=0.300]hub/scripts/apply_agent_finding.py",
    "root_cause": "_get_recent_agent_findings",
    "fix_script": "Ensure DB connection is always closed using try/finally",
    "when": "2026-04-22 23:25"
  }
}